r4l/__init__.py
r4l/main-jp.py
r4l/main.py
reading4listeners/__init__.py
reading4listeners/main-jp.py
reading4listeners/main.py
reading4listeners-0.0.4.post2.dist-info/LICENSE
reading4listeners-0.0.4.post2.dist-info/METADATA
reading4listeners-0.0.4.post2.dist-info/WHEEL
reading4listeners-0.0.4.post2.dist-info/entry_points.txt
reading4listeners-0.0.4.post2.dist-info/top_level.txt
reading4listeners-0.0.4.post2.dist-info/RECORD
