Metadata-Version: 2.1
Name: reading4listeners
Version: 0.0.4.post2
Summary: A deep-learning powered application which turns pdfs into audio files. Featuring ocr improvement and tts with inflection!
Home-page: https://github.com/CypherousSkies/reading-for-listeners
Author: CypherousSkies
Author-email: 5472563+CypherousSkies@users.noreply.github.com
License: AGPL-3
Project-URL: Bug Tracker, https://github.com/CypherousSkies/reading-for-listeners/issues
Platform: UNKNOWN
License-File: LICENSE
Requires-Dist: TTS
Requires-Dist: nltk
Requires-Dist: psutil
Requires-Dist: pydub
Requires-Dist: tqdm
Requires-Dist: ocrmypdf
Requires-Dist: transformers
Requires-Dist: pyspellchecker
Requires-Dist: torch
Requires-Dist: opencv-python
Requires-Dist: pdf2image
Requires-Dist: numpy
Requires-Dist: scipy
